JIRALibrary/__init__.py
JIRALibrary/keywords.py
robotframework_jira-0.0.3.dist-info/LICENSE
robotframework_jira-0.0.3.dist-info/METADATA
robotframework_jira-0.0.3.dist-info/WHEEL
robotframework_jira-0.0.3.dist-info/top_level.txt
robotframework_jira-0.0.3.dist-info/RECORD
